[{
    "author": {
      "firstName": "Chat",
      "id": "e52552f4-835d-4dbe-ba77-b076e659774d",
      "imageUrl": "https://i.pravatar.cc/300?u=e52552f4-835d-4dbe-ba77-b076e659774d",
      "lastName": "BoT"
    },
    "createdAt": 1655624462001,
    "id": "22212d42-1252-4641-9786-d6f83b2ce4a8",
    "status": "seen",
    "text": "Incorrect",
    "type": "text"
  },
    {
      "author": {
        "firstName": "Nahid",
        "id": "82091008-a484-4a89-ae75-a22bf8d6f3ac",
        "lastName": "Hasan"
      },
      "createdAt": 1655624462002,
      "id": "113bb2e8-f74e-42cd-aa30-4085a0f52c58",
      "status": "seen",
      "text": "i rice eat.",
      "type": "text"
    },
    {
      "author": {
        "firstName": "Chat",
        "id": "e52552f4-835d-4dbe-ba77-b076e659774d",
        "imageUrl": "https://i.pravatar.cc/300?u=e52552f4-835d-4dbe-ba77-b076e659774d",
        "lastName": "BoT"
      },
      "createdAt": 1655624462001,
      "id": "22212d42-1252-4641-9786-d6f83b2ce4a8",
      "status": "seen",
      "text": "Correct",
      "type": "text"
    },
    {
        "author": {
          "firstName": "Nahid",
          "id": "82091008-a484-4a89-ae75-a22bf8d6f3ac",
          "lastName": "Hasan"
        },
        "createdAt": 1655624462002,
        "id": "113bb2e8-f74e-42cd-aa30-4085a0f52c58",
        "status": "seen",
        "text": "I eat rice.",
        "type": "text"
      },
      {
        "author": {
          "firstName": "Chat",
          "id": "e52552f4-835d-4dbe-ba77-b076e659774d",
          "imageUrl": "https://i.pravatar.cc/300?u=e52552f4-835d-4dbe-ba77-b076e659774d",
          "lastName": "BoT"
        },
        "createdAt": 1655624462001,
        "id": "22212d42-1252-4641-9786-d6f83b2ce4a8",
        "status": "seen",
        "text": "Correct",
        "type": "text"
      },
      {
        "author": {
          "firstName": "Nahid",
          "id": "82091008-a484-4a89-ae75-a22bf8d6f3ac",
          "lastName": "Hasan"
        },
        "createdAt": 1655624462003,
        "id": "f6c82613-1e50-45d5-afdf-4ad8558a0a13",
        "status": "seen",
        "text": "What did you have for breakfast?",
        "type": "text"
      }
  ]